girth/__init__.py
girth/common/__init__.py
girth/common/cronbach_alpha.py
girth/common/entropy.py
girth/common/hypersphere.py
girth/common/polychoric.py
girth/common/polyserial.py
girth/common/procrustes.py
girth/common/reverse.py
girth/factoranalysis/__init__.py
girth/factoranalysis/maximum_likelihood.py
girth/factoranalysis/minimum_rank.py
girth/factoranalysis/paf.py
girth/factoranalysis/pca.py
girth/factoranalysis/rotation.py
girth/multidimensional/__init__.py
girth/multidimensional/multidimensional_ability_methods.py
girth/multidimensional/multidimensional_initial_guess.py
girth/multidimensional/multidimensional_mml_methods.py
girth/multidimensional/partial_integral_md.py
girth/synthetic/__init__.py
girth/synthetic/dichotomous.py
girth/synthetic/polytomous.py
girth/unidimensional/dichotomous/__init__.py
girth/unidimensional/dichotomous/ability_estimation.py
girth/unidimensional/dichotomous/ability_threepl.py
girth/unidimensional/dichotomous/jml_methods.py
girth/unidimensional/dichotomous/partial_integrals.py
girth/unidimensional/dichotomous/rasch_conditional.py
girth/unidimensional/dichotomous/rasch_mml.py
girth/unidimensional/dichotomous/threepl_mml.py
girth/unidimensional/dichotomous/twopl_mml.py
girth/unidimensional/dichotomous/twopl_mml_eap.py
girth/unidimensional/polytomous/__init__.py
girth/unidimensional/polytomous/ability_estimation_poly.py
girth/unidimensional/polytomous/grm_jml.py
girth/unidimensional/polytomous/grm_mml.py
girth/unidimensional/polytomous/grm_mml_eap.py
girth/unidimensional/polytomous/gum_mml.py
girth/unidimensional/polytomous/partial_integrals_poly.py
girth/unidimensional/polytomous/pcm_jml.py
girth/unidimensional/polytomous/pcm_mml.py
girth/utilities/__init__.py
girth/utilities/bootstrap_errors.py
girth/utilities/ctt_statistics.py
girth/utilities/girth_options.py
girth/utilities/latent_ability_distribution.py
girth/utilities/look_up_table.py
girth/utilities/polytomous_utils.py
girth/utilities/utils.py
girth-0.8.0.dist-info/LICENSE.txt
girth-0.8.0.dist-info/METADATA
girth-0.8.0.dist-info/WHEEL
girth-0.8.0.dist-info/top_level.txt
girth-0.8.0.dist-info/RECORD
