Metadata-Version: 2.1
Name: girth
Version: 0.8.0
Summary: A python package for Item Response Theory.
Home-page: https://eribean.github.io/girth/
Author: Ryan C. Sanchez
Author-email: ryan.sanchez@gofactr.com
License: MIT
Keywords: IRT,Psychometrics,Item Response Theory,Computer Adaptive Testing,Psychology
Platform: UNKNOWN
Classifier: Development Status :: 3 - Alpha
Classifier: Intended Audience :: Science/Research
Classifier: Topic :: Scientific/Engineering
Classifier: License :: OSI Approved :: MIT License
Classifier: Programming Language :: Python :: 3.8
Classifier: Programming Language :: Python :: 3.9
License-File: LICENSE.txt
